auditize/__init__.py
auditize/__main__.py
auditize/config.py
auditize/dependencies.py
auditize/exceptions.py
auditize/logger.py
auditize/openapi.py
auditize/scheduler.py
auditize/version.py
auditize/api/__init__.py
auditize/api/exception.py
auditize/api/validation.py
auditize/api/models/__init__.py
auditize/api/models/common.py
auditize/api/models/cursor_pagination.py
auditize/api/models/dates.py
auditize/api/models/page_pagination.py
auditize/api/models/search.py
auditize/apikey/__init__.py
auditize/apikey/api.py
auditize/apikey/models.py
auditize/apikey/service.py
auditize/apikey/sql_models.py
auditize/app/__init__.py
auditize/app/app_api.py
auditize/app/app_static.py
auditize/app/cors.py
auditize/auth/__init__.py
auditize/auth/api.py
auditize/auth/authorizer.py
auditize/auth/constants.py
auditize/auth/jwt.py
auditize/data/html/auditize-web-component.mjs
auditize/data/html/index.html
auditize/data/html/assets/favicon-CmRhlul4.png
auditize/data/html/assets/index-C9XJM3D_.css
auditize/data/html/assets/index-CuyfwLWv.js
auditize/data/html/assets/json-Cp-IABpG.js
auditize/data/html/assets/wasm-CG6Dc4jp.js
auditize/database/__init__.py
auditize/database/alembic.ini
auditize/database/dbm.py
auditize/database/elastic.py
auditize/database/alembic/env.py
auditize/database/alembic/versions/30a9e8657024_initial_migration.py
auditize/database/alembic/versions/51496d22ec2a_add_repo_reindex_progress.py
auditize/database/sql/__init__.py
auditize/database/sql/models.py
auditize/database/sql/service.py
auditize/helpers/__init__.py
auditize/helpers/datetime.py
auditize/helpers/email.py
auditize/helpers/string.py
auditize/i18n/__init__.py
auditize/i18n/detection.py
auditize/i18n/lang.py
auditize/i18n/translator.py
auditize/i18n/translations/en.json
auditize/i18n/translations/fr.json
auditize/info/__init__.py
auditize/info/api.py
auditize/info/models.py
auditize/log/__init__.py
auditize/log/api.py
auditize/log/csv.py
auditize/log/index.py
auditize/log/jsonl.py
auditize/log/models.py
auditize-0.10.0.dist-info/METADATA
auditize-0.10.0.dist-info/WHEEL
auditize-0.10.0.dist-info/entry_points.txt
auditize-0.10.0.dist-info/top_level.txt
auditize-0.10.0.dist-info/RECORD
